cdk_cloudformation_snyk_container_helm/__init__.py
cdk_cloudformation_snyk_container_helm/py.typed
cdk_cloudformation_snyk_container_helm/_jsii/__init__.py
cdk_cloudformation_snyk_container_helm/_jsii/snyk-container-helm@1.2.0-alpha.7.jsii.tgz
cdk_cloudformation_snyk_container_helm-1.2.0a7.dist-info/LICENSE
cdk_cloudformation_snyk_container_helm-1.2.0a7.dist-info/METADATA
cdk_cloudformation_snyk_container_helm-1.2.0a7.dist-info/WHEEL
cdk_cloudformation_snyk_container_helm-1.2.0a7.dist-info/top_level.txt
cdk_cloudformation_snyk_container_helm-1.2.0a7.dist-info/RECORD
